ib_async_mcp/__init__.py
ib_async_mcp/server.py
ib_async_mcp-0.1.1.dist-info/METADATA
ib_async_mcp-0.1.1.dist-info/WHEEL
ib_async_mcp-0.1.1.dist-info/entry_points.txt
ib_async_mcp-0.1.1.dist-info/RECORD
