Metadata-Version: 2.4
Name: ib-async-mcp
Version: 0.1.1
Summary: MCP server wrapping ib_async for Interactive Brokers API
Project-URL: Homepage, https://github.com/atomcp-ai/ib-async-mcp
Project-URL: Repository, https://github.com/atomcp-ai/ib-async-mcp
Project-URL: Issues, https://github.com/atomcp-ai/ib-async-mcp/issues
Author: atomcp-ai
License: MIT
Keywords: api,ib-async,interactive-brokers,mcp,trading
Classifier: Development Status :: 4 - Beta
Classifier: Intended Audience :: Developers
Classifier: License :: OSI Approved :: MIT License
Classifier: Programming Language :: Python :: 3
Classifier: Programming Language :: Python :: 3.10
Classifier: Programming Language :: Python :: 3.11
Classifier: Programming Language :: Python :: 3.12
Requires-Python: >=3.10
Requires-Dist: ib-async>=1.0.0
Requires-Dist: mcp>=1.0.0
